spawningtool/__init__.py
spawningtool/__main__.py
spawningtool/analyzer.py
spawningtool/coop_constants.py
spawningtool/exception.py
spawningtool/hots_constants.py
spawningtool/lotv_constants.py
spawningtool/parser.py
spawningtool-2.10.0.dist-info/DESCRIPTION.rst
spawningtool-2.10.0.dist-info/METADATA
spawningtool-2.10.0.dist-info/RECORD
spawningtool-2.10.0.dist-info/WHEEL
spawningtool-2.10.0.dist-info/entry_points.txt
spawningtool-2.10.0.dist-info/metadata.json
spawningtool-2.10.0.dist-info/top_level.txt
tests/__init__.py
tests/__main__.py
tests/utils.py
