Metadata-Version: 2.0
Name: spawningtool
Version: 2.10.0
Summary: Build order parser for StarCraft 2 replays
Home-page: https://github.com/StoicLoofah/spawningtool
Author: Kevin Leung
Author-email: kkleung89@gmail.com
License: UNKNOWN
Platform: UNKNOWN
Classifier: Environment :: Console
Classifier: Intended Audience :: Developers
Classifier: Natural Language :: English
Classifier: Operating System :: OS Independent
Classifier: Programming Language :: Python
Classifier: Programming Language :: Python :: 2.7
Classifier: Programming Language :: Python :: 3.4
Classifier: Topic :: Games/Entertainment
Classifier: Topic :: Games/Entertainment :: Real Time Strategy
Requires-Dist: argparse
Requires-Dist: sc2reader (>=1.6.0)
